azulero/__init__.py
azulero/assemble.py
azulero/client.py
azulero/color.py
azulero/crop.py
azulero/find.py
azulero/io.py
azulero/mask.py
azulero/overlay.py
azulero/process.py
azulero/retrieve.py
azulero/roam.py
azulero/sequence.py
azulero/spot.py
azulero/stats.py
azulero/timing.py
azulero/tune.py
azulero-1.1.1.dist-info/METADATA
azulero-1.1.1.dist-info/WHEEL
azulero-1.1.1.dist-info/entry_points.txt
azulero-1.1.1.dist-info/licenses/LICENSE
azulero-1.1.1.dist-info/RECORD
