Metadata-Version: 2.4
Name: azulero
Version: 1.1.1
Summary: Bring colors to Euclid tiles!
Project-URL: Homepage, https://github.com/kabasset/azulero
Project-URL: Issues, https://github.com/kabasset/azulero/issues
Author-email: Antoine Basset <antoine.basset@cnes.fr>
License-Expression: Apache-2.0
License-File: LICENSE
Classifier: Operating System :: OS Independent
Classifier: Programming Language :: Python :: 3
Requires-Python: >=3.8
Requires-Dist: astropy
Requires-Dist: astroquery
Requires-Dist: matplotlib
Requires-Dist: numpy>=2.0
Requires-Dist: opencv-python
Requires-Dist: pyyaml
Requires-Dist: requests
Requires-Dist: scikit-image
Requires-Dist: scipy
Requires-Dist: shapely
